{
  "profile": {
    "unitid": 102313,
    "name": "H Councill Trenholm State Community College",
    "city": "Troy",
    "state": "AL",
    "control": "Public",
    "level": "2-year",
    "carnegie_basic": "Associate's Colleges: High Career & Technical-High Traditional",
    "website": "www.troy.edu/",
    "admissions_url": null,
    "test_policy": "Test optional",
    "major_families": [
      "Engineering Technologies",
      "Health Professions",
      "Personal & Culinary Services",
      "Computer & Information Sciences"
    ],
    "intl_enrollment_pct": 0,
    "tuition_summary": {
      "sticker": 4890.0,
      "in_state": 4830.0,
      "out_of_state": 8580.0
    },
    "outcomes": {
      "acceptance_rate": null,
      "yield": null,
      "grad_rate_6yr": null,
      "retention_full_time": 50,
      "student_faculty_ratio": 16,
      "total_enrollment": 1907
    }
  },
  "requirements": {
    "required": [],
    "considered": [],
    "not_considered": [],
    "test_policy": "Test optional"
  },
  "support_notes": {
    "international_cost": null,
    "scholarships": null,
    "support_services": null,
    "deadlines": null
  }
}