{
  "profile": {
    "unitid": 130253,
    "name": "Sacred Heart University",
    "city": "Fairfield",
    "state": "CT",
    "control": "Private nonprofit",
    "level": "4-year",
    "carnegie_basic": "Doctoral/Professional Universities",
    "website": "https://www.sacredheart.edu/",
    "admissions_url": null,
    "test_policy": "Test optional",
    "major_families": [
      "Health Professions",
      "Business, Management & Marketing",
      "Education",
      "Biological & Biomedical Sciences"
    ],
    "intl_enrollment_pct": 18,
    "tuition_summary": {
      "sticker": 48460.0,
      "in_state": 46580.0,
      "out_of_state": 46580.0
    },
    "outcomes": {
      "acceptance_rate": 68,
      "yield": 20,
      "grad_rate_6yr": 74,
      "retention_full_time": 85,
      "student_faculty_ratio": 16,
      "total_enrollment": 11179
    }
  },
  "requirements": {
    "required": [
      "English Proficiency Test",
      "Personal Statement Or Essay",
      "Recommendations",
      "Secondary School Gpa",
      "Secondary School Record"
    ],
    "considered": [
      "Completion Of College Preparatory Program",
      "Formal Demonstration Of Competencies",
      "Secondary School Rank",
      "Work Experience"
    ],
    "not_considered": [
      "Admission Test Scores",
      "Legacy Status",
      "Other Test Wonderlic Wisc Iii Etc"
    ],
    "test_policy": "Test optional"
  },
  "support_notes": {
    "international_cost": null,
    "scholarships": null,
    "support_services": null,
    "deadlines": null
  }
}