{
  "profile": {
    "unitid": 165671,
    "name": "Emmanuel College",
    "city": "North Andover",
    "state": "MA",
    "control": "Private nonprofit",
    "level": "4-year",
    "carnegie_basic": "Baccalaureate Colleges: Arts & Sciences Focus",
    "website": "https://www.merrimack.edu/",
    "admissions_url": null,
    "test_policy": "Test flexible",
    "major_families": [
      "Business, Management & Marketing",
      "Biological & Biomedical Sciences",
      "Social Sciences",
      "Health Professions"
    ],
    "intl_enrollment_pct": 1,
    "tuition_summary": {
      "sticker": 46686.0,
      "in_state": 44908.0,
      "out_of_state": 44908.0
    },
    "outcomes": {
      "acceptance_rate": 81,
      "yield": 11,
      "grad_rate_6yr": 66,
      "retention_full_time": 79,
      "student_faculty_ratio": 13,
      "total_enrollment": 2059
    }
  },
  "requirements": {
    "required": [
      "Completion Of College Preparatory Program",
      "English Proficiency Test",
      "Personal Statement Or Essay",
      "Recommendations",
      "Secondary School Gpa",
      "Secondary School Record"
    ],
    "considered": [
      "Admission Test Scores",
      "Secondary School Rank"
    ],
    "not_considered": [
      "Formal Demonstration Of Competencies",
      "Legacy Status",
      "Other Test Wonderlic Wisc Iii Etc",
      "Work Experience"
    ],
    "test_policy": "Test flexible"
  },
  "support_notes": {
    "international_cost": null,
    "scholarships": null,
    "support_services": null,
    "deadlines": null
  }
}