{
  "profile": {
    "unitid": 181853,
    "name": "York University",
    "city": "Concord",
    "state": "NH",
    "control": "Private nonprofit",
    "level": "4-year",
    "carnegie_basic": "Baccalaureate Colleges: Diverse Fields",
    "website": "https://www.granite.edu/",
    "admissions_url": null,
    "test_policy": "Test flexible",
    "major_families": [
      "Education",
      "Business, Management & Marketing",
      "Liberal Arts & Humanities",
      "Biological & Biomedical Sciences"
    ],
    "intl_enrollment_pct": 11,
    "tuition_summary": {
      "sticker": 21600.0,
      "in_state": 20900.0,
      "out_of_state": 20900.0
    },
    "outcomes": {
      "acceptance_rate": 48,
      "yield": 47,
      "grad_rate_6yr": 37,
      "retention_full_time": 67,
      "student_faculty_ratio": 11,
      "total_enrollment": 585
    }
  },
  "requirements": {
    "required": [
      "English Proficiency Test",
      "Secondary School Gpa",
      "Secondary School Record"
    ],
    "considered": [
      "Admission Test Scores",
      "Completion Of College Preparatory Program",
      "Secondary School Rank"
    ],
    "not_considered": [
      "Formal Demonstration Of Competencies",
      "Legacy Status",
      "Other Test Wonderlic Wisc Iii Etc",
      "Personal Statement Or Essay",
      "Recommendations",
      "Work Experience"
    ],
    "test_policy": "Test flexible"
  },
  "support_notes": {
    "international_cost": null,
    "scholarships": null,
    "support_services": null,
    "deadlines": null
  }
}