{
  "profile": {
    "unitid": 189273,
    "name": "Beth Hamedrash Shaarei Yosher Institute",
    "city": "Staten Island",
    "state": "NY",
    "control": "Private nonprofit",
    "level": "4-year",
    "carnegie_basic": "Not applicable, not in Carnegie universe (not accredited or nondegree-granting)",
    "website": "www.csi.cuny.edu/",
    "admissions_url": null,
    "test_policy": "Test optional",
    "major_families": [
      "Philosophy & Religious Studies"
    ],
    "intl_enrollment_pct": 0,
    "tuition_summary": {
      "sticker": 12000.0,
      "in_state": 12000.0,
      "out_of_state": 12000.0
    },
    "outcomes": {
      "acceptance_rate": 90,
      "yield": 96,
      "grad_rate_6yr": 10,
      "retention_full_time": 84,
      "student_faculty_ratio": 12,
      "total_enrollment": 83
    }
  },
  "requirements": {
    "required": [
      "Completion Of College Preparatory Program",
      "Recommendations"
    ],
    "considered": [
      "Formal Demonstration Of Competencies",
      "Legacy Status",
      "Personal Statement Or Essay",
      "Secondary School Gpa",
      "Secondary School Record"
    ],
    "not_considered": [
      "Admission Test Scores",
      "English Proficiency Test",
      "Other Test Wonderlic Wisc Iii Etc",
      "Secondary School Rank",
      "Work Experience"
    ],
    "test_policy": "Test optional"
  },
  "support_notes": {
    "international_cost": null,
    "scholarships": null,
    "support_services": null,
    "deadlines": null
  }
}