{
  "profile": {
    "unitid": 230038,
    "name": "Brigham Young University",
    "city": "Provo",
    "state": "UT",
    "control": "Private nonprofit",
    "level": "4-year",
    "carnegie_basic": "Doctoral Universities: High Research Activity",
    "website": "www.byu.edu/",
    "admissions_url": null,
    "test_policy": "Test flexible",
    "major_families": [
      "Business, Management & Marketing",
      "Biological & Biomedical Sciences",
      "Engineering",
      "Computer & Information Sciences"
    ],
    "intl_enrollment_pct": 3,
    "tuition_summary": {
      "sticker": 6496.0,
      "in_state": 6304.0,
      "out_of_state": 6304.0
    },
    "outcomes": {
      "acceptance_rate": 69,
      "yield": 80,
      "grad_rate_6yr": 82,
      "retention_full_time": 89,
      "student_faculty_ratio": 21,
      "total_enrollment": 35074
    }
  },
  "requirements": {
    "required": [
      "English Proficiency Test",
      "Personal Statement Or Essay",
      "Recommendations",
      "Secondary School Gpa",
      "Secondary School Record"
    ],
    "considered": [
      "Admission Test Scores",
      "Completion Of College Preparatory Program",
      "Work Experience"
    ],
    "not_considered": [
      "Formal Demonstration Of Competencies",
      "Legacy Status",
      "Other Test Wonderlic Wisc Iii Etc",
      "Secondary School Rank"
    ],
    "test_policy": "Test flexible"
  },
  "support_notes": {
    "international_cost": null,
    "scholarships": null,
    "support_services": null,
    "deadlines": null
  }
}