{
  "profile": {
    "unitid": 451404,
    "name": "Talmudical Seminary of Bobov",
    "city": "Brooklyn",
    "state": "NY",
    "control": "Private nonprofit",
    "level": "4-year",
    "carnegie_basic": "Special Focus Four-Year: Faith-Related Institutions",
    "website": "www.independentrabbinicalcolleges.org/",
    "admissions_url": null,
    "test_policy": "Test optional",
    "major_families": [
      "Philosophy & Religious Studies"
    ],
    "intl_enrollment_pct": 0,
    "tuition_summary": {
      "sticker": 13200.0,
      "in_state": 12600.0,
      "out_of_state": 12600.0
    },
    "outcomes": {
      "acceptance_rate": 98,
      "yield": 98,
      "grad_rate_6yr": 43,
      "retention_full_time": 77,
      "student_faculty_ratio": 10,
      "total_enrollment": 515
    }
  },
  "requirements": {
    "required": [
      "Completion Of College Preparatory Program",
      "Recommendations"
    ],
    "considered": [
      "Legacy Status",
      "Personal Statement Or Essay",
      "Secondary School Record",
      "Work Experience"
    ],
    "not_considered": [
      "Admission Test Scores",
      "English Proficiency Test",
      "Formal Demonstration Of Competencies",
      "Other Test Wonderlic Wisc Iii Etc",
      "Secondary School Gpa",
      "Secondary School Rank"
    ],
    "test_policy": "Test optional"
  },
  "support_notes": {
    "international_cost": null,
    "scholarships": null,
    "support_services": null,
    "deadlines": null
  }
}