{
  "profile": {
    "unitid": 177065,
    "name": "Columbia College",
    "city": "Columbia",
    "state": "MO",
    "control": "Private nonprofit",
    "level": "4-year",
    "carnegie_basic": "Master's Colleges & Universities: Larger Programs",
    "website": "https://www.ccis.edu/",
    "admissions_url": null,
    "test_policy": "Test optional",
    "major_families": [
      "Business, Management & Marketing",
      "Liberal Arts & Humanities",
      "Homeland Security & Law Enforcement",
      "Health Professions"
    ],
    "intl_enrollment_pct": 4,
    "tuition_summary": {
      "sticker": 24326.0,
      "in_state": 24326.0,
      "out_of_state": 24326.0
    },
    "outcomes": {
      "acceptance_rate": null,
      "yield": null,
      "grad_rate_6yr": 42,
      "retention_full_time": 67,
      "student_faculty_ratio": 20,
      "total_enrollment": 6046
    }
  },
  "requirements": {
    "required": [],
    "considered": [],
    "not_considered": [],
    "test_policy": "Test optional"
  },
  "support_notes": {
    "international_cost": null,
    "scholarships": null,
    "support_services": null,
    "deadlines": null
  }
}