{
  "profile": {
    "unitid": 497107,
    "name": "University of Silicon Andhra",
    "city": "Milpitas",
    "state": "CA",
    "control": "Private nonprofit",
    "level": "4-year",
    "carnegie_basic": "Not applicable, not in Carnegie universe (not accredited or nondegree-granting)",
    "website": "https://www.uofsa.edu/",
    "admissions_url": null,
    "test_policy": "Test optional",
    "major_families": [
      "Visual & Performing Arts",
      "Foreign Languages & Linguistics"
    ],
    "intl_enrollment_pct": 40,
    "tuition_summary": {
      "sticker": null,
      "in_state": null,
      "out_of_state": null
    },
    "outcomes": {
      "acceptance_rate": 95,
      "yield": 86,
      "grad_rate_6yr": null,
      "retention_full_time": null,
      "student_faculty_ratio": 12,
      "total_enrollment": 249
    }
  },
  "requirements": {
    "required": [
      "Formal Demonstration Of Competencies"
    ],
    "considered": [
      "Recommendations"
    ],
    "not_considered": [
      "Admission Test Scores",
      "Completion Of College Preparatory Program",
      "English Proficiency Test",
      "Legacy Status",
      "Other Test Wonderlic Wisc Iii Etc",
      "Personal Statement Or Essay",
      "Secondary School Gpa",
      "Secondary School Rank",
      "Secondary School Record",
      "Work Experience"
    ],
    "test_policy": "Test optional"
  },
  "support_notes": {
    "international_cost": null,
    "scholarships": null,
    "support_services": null,
    "deadlines": null
  }
}